{
  "symbol": "else",
  "name": "Electro-Sensors, Inc.",
  "ipoYear": null,
  "sector": "Capital Goods",
  "industry": "Industrial Machinery/Components",
  "exchange": "nasdaq",
  "category": "INDUSTRIAL INSTRUMENTS FOR MEASUREMENT, DISPLAY, AND CONTROL",
  "address": {
    "street1": "6111 BLUE CIRCLE DR",
    "city": "MINNETONKA",
    "state": "MN",
    "zip": "55343-9108"
  },
  "profit": {
    "2010": 527000,
    "2011": 548000,
    "2012": 1086000,
    "2013": 706000
  },
  "cash": {
    "2009": 746000,
    "2010": 583000,
    "2011": 5476000,
    "2012": 1102000,
    "2013": 1505000
  },
  "earningsPerShare": {
    "2010": 0.16,
    "2011": 0.16,
    "2012": 0.32,
    "2013": 0.2
  },
  "htmlUrl": "http://www.sec.gov/Archives/edgar/data/351789/000089710114000358/0000897101-14-000358-index.htm",
  "xmlUrl": "http://www.sec.gov/Archives/edgar/data/351789/000089710114000358/else-20131231.xml"
}