{
  "symbol": "eqix",
  "name": "Equinix, Inc.",
  "ipoYear": 2000,
  "sector": "Public Utilities",
  "industry": "Telecommunications Equipment",
  "exchange": "nasdaq",
  "category": "TELEPHONE COMMUNICATIONS (NO RADIO TELEPHONE)",
  "address": {
    "street1": "ONE LAGOON DRIVE, 4TH FLOOR",
    "city": "REDWOOD CITY",
    "state": "CA",
    "zip": "94065"
  },
  "profit": {
    "2009": 69431000,
    "2010": 36881000,
    "2011": 94776000,
    "2012": 140028000,
    "2013": 94685000
  },
  "cash": {
    "2009": 346056000,
    "2010": 442841000,
    "2011": 278823000,
    "2012": 252213000,
    "2013": 685019000
  },
  "earningsPerShare": {
    "2009": 1.8,
    "2010": 0.84,
    "2011": 1.77,
    "2012": 2.92,
    "2013": 1.92
  },
  "htmlUrl": "http://www.sec.gov/Archives/edgar/data/1101239/000119312514076710/0001193125-14-076710-index.htm",
  "xmlUrl": "http://www.sec.gov/Archives/edgar/data/1101239/000119312514076710/eqix-20131231.xml"
}