{
  "symbol": "frp",
  "name": "FairPoint Communications, Inc.",
  "ipoYear": null,
  "sector": "Public Utilities",
  "industry": "Telecommunications Equipment",
  "exchange": "nasdaq",
  "category": "TELEPHONE COMMUNICATIONS (NO RADIO TELEPHONE)",
  "address": {
    "street1": "521 EAST MOREHEAD ST",
    "city": "CHARLOTTE",
    "state": "NC",
    "zip": "28202"
  },
  "profit": {
    "2009": -241396000,
    "2010": -281579000,
    "2012": -153294000,
    "2013": -93450000
  },
  "cash": {},
  "earningsPerShare": {
    "2009": -2.7,
    "2010": -3.15,
    "2012": -5.9,
    "2013": -3.57
  },
  "htmlUrl": "http://www.sec.gov/Archives/edgar/data/1062613/000106261314000012/0001062613-14-000012-index.htm",
  "xmlUrl": "http://www.sec.gov/Archives/edgar/data/1062613/000106261314000012/frp-20131231.xml"
}