{
  "symbol": "gtxi",
  "name": "GTx, Inc.",
  "ipoYear": 2004,
  "sector": "Health Care",
  "industry": "Major Pharmaceuticals",
  "exchange": "nasdaq",
  "category": "PHARMACEUTICAL PREPARATIONS",
  "address": {
    "street1": "175 TOYOTA PLAZA",
    "city": "MEMPHIS",
    "state": "TN",
    "zip": "38103"
  },
  "profit": {
    "2009": -46256000,
    "2010": 15294000,
    "2011": -33294000,
    "2012": -27075000,
    "2013": -42111000
  },
  "cash": {
    "2009": 40219000,
    "2010": 58181000,
    "2011": 63745000,
    "2012": 48044000,
    "2013": 14529000
  },
  "earningsPerShare": {},
  "htmlUrl": "http://www.sec.gov/Archives/edgar/data/1260990/000110465914018791/0001104659-14-018791-index.htm",
  "xmlUrl": "http://www.sec.gov/Archives/edgar/data/1260990/000110465914018791/gtxi-20131231.xml"
}