{
  "symbol": "hbk",
  "name": "Hamilton Bancorp, Inc.",
  "ipoYear": 2012,
  "sector": "Finance",
  "industry": "Savings Institutions",
  "exchange": "nasdaq",
  "category": "SAVINGS INSTITUTION, FEDERALLY CHARTERED",
  "address": {
    "street1": "501 FAIRMOUNT AVE, SUITE 200",
    "city": "TOWSON",
    "state": "MD",
    "zip": "21286"
  },
  "profit": {
    "2012": 131019,
    "2013": -172135,
    "2014": -1195384
  },
  "cash": {
    "2011": 39473433,
    "2012": 35249548,
    "2013": 33968744,
    "2014": 33073310
  },
  "earningsPerShare": {
    "2013": -0.05
  },
  "htmlUrl": "http://www.sec.gov/Archives/edgar/data/1551739/000119312514257850/0001193125-14-257850-index.htm",
  "xmlUrl": "http://www.sec.gov/Archives/edgar/data/1551739/000119312514257850/hbk-20140331.xml"
}