{
  "symbol": "hcbk",
  "name": "Hudson City Bancorp, Inc.",
  "ipoYear": null,
  "sector": "Finance",
  "industry": "Banks",
  "exchange": "nasdaq",
  "category": "SAVINGS INSTITUTIONS, NOT FEDERALLY CHARTERED",
  "address": {
    "street1": "WEST 80 CENTURY RD",
    "city": "PARAMUS",
    "state": "NJ",
    "zip": "07652"
  },
  "profit": {
    "2009": 527244000,
    "2010": 537206000,
    "2011": -735989000,
    "2012": 249143000,
    "2013": 185216000
  },
  "cash": {
    "2009": 561201000,
    "2010": 669397000,
    "2011": 754080000,
    "2012": 827968000,
    "2013": 4324474000
  },
  "earningsPerShare": {
    "2009": 1.08,
    "2010": 1.09,
    "2011": -1.49,
    "2012": 0.5,
    "2013": 0.37
  },
  "htmlUrl": "http://www.sec.gov/Archives/edgar/data/921847/000119312514171406/0001193125-14-171406-index.htm"
}